trado.py
trado-0.4.2.dist-info/entry_points.txt
trado-0.4.2.dist-info/LICENSE
trado-0.4.2.dist-info/WHEEL
trado-0.4.2.dist-info/METADATA
trado-0.4.2.dist-info/RECORD
