Metadata-Version: 2.1
Name: trado
Version: 0.4.2
Summary: Dumb and dirty docker-compose files generator for traefik exposing
License: Unlicense
Author: Grigory Bakunov
Author-email: thebobuk@ya.ru
Requires-Python: >=3.9,<4.0
Classifier: License :: Other/Proprietary License
Classifier: Programming Language :: Python :: 3
Classifier: Programming Language :: Python :: 3.10
Classifier: Programming Language :: Python :: 3.9
Requires-Dist: PyYAML (>=6.0,<7.0)
